shadowsocks/__init__.py
shadowsocks/asyncdns.py
shadowsocks/common.py
shadowsocks/daemon.py
shadowsocks/encrypt.py
shadowsocks/eventloop.py
shadowsocks/local.py
shadowsocks/lru_cache.py
shadowsocks/manager.py
shadowsocks/server.py
shadowsocks/shell.py
shadowsocks/tcprelay.py
shadowsocks/udprelay.py
shadowsocks/crypto/__init__.py
shadowsocks/crypto/openssl.py
shadowsocks/crypto/rc4_md5.py
shadowsocks/crypto/sodium.py
shadowsocks/crypto/table.py
shadowsocks/crypto/util.py
shadowsocks_fixed-2.8.5.dist-info/LICENSE
shadowsocks_fixed-2.8.5.dist-info/METADATA
shadowsocks_fixed-2.8.5.dist-info/WHEEL
shadowsocks_fixed-2.8.5.dist-info/top_level.txt
shadowsocks_fixed-2.8.5.dist-info/RECORD
