Metadata-Version: 2.1
Name: shadowsocks-fixed
Version: 2.8.5
Summary: A fixed version of Shadowsocks with Python 3.10+ and OpenSSL 1.1+ compatibility
Home-page: https://github.com/yourusername/shadowsocks-fixed
Author: Your Name
Author-email: your.email@example.com
License: Apache License 2.0
License-File: LICENSE
Requires-Dist: pycryptodome
